{
  "generated_at": "2026-04-01T22:24:21.754452+08:00",
  "total_titles_processed": 1899,
  "failed_sources": [],
  "trends": [
    {
      "keyword_group": "美股",
      "match_count": 30,
      "titles": [
        {
          "title": "美伊均释放结束中东冲突意愿，美股大涨、纳指飙升近4%，原油重挫，金银大涨",
          "url": "https://wallstreetcn.com/articles/3768819",
          "source": "华尔街见闻",
          "ranks": [
            1
          ],
          "is_new": false,
          "appearance_count": 12,
          "time_info": "[07时23分 ~ 22时24分]"
        },
        {
          "title": "特朗普释放停战信号，美股指涨幅扩大，纳指涨逾2%，房利美、房地美涨超10%，金银油齐涨",
          "url": "https://wallstreetcn.com/articles/3768819",
          "source": "华尔街见闻",
          "ranks": [
            2
          ],
          "is_new": false,
          "appearance_count": 9,
          "time_info": "[00时50分 ~ 06时23分]"
        },
        {
          "title": "【早报】伊朗总统：愿在诉求满足前提下结束战争；美股大涨，科技股、中概股大幅走强",
          "url": "https://www.cls.cn/detail/2331350",
          "source": "财联社热门",
          "ranks": [
            1
          ],
          "is_new": false,
          "appearance_count": 4,
          "time_info": "[09时16分 ~ 14时20分]"
        },
        {
          "title": "美股三大股指集体收涨纳指涨超3.8%",
          "url": "https://www.toutiao.com/trending/7623563069813165609/",
          "source": "今日头条",
          "ranks": [
            4
          ],
          "is_new": false,
          "appearance_count": 2,
          "time_info": "[09时16分 ~ 09时17分]"
        },
        {
          "title": "耐克美股盘前跌超9%，此前公司意外下调第四财季销售额预期。",
          "url": "https://wallstreetcn.com/livenews/3080739",
          "source": "华尔街见闻-快讯",
          "ranks": [
            2
          ],
          "is_new": false,
          "appearance_count": 1,
          "time_info": "16时08分"
        },
        {
          "title": "美股短线走强，纳指涨超3%，标普500指数、道指涨超2%。",
          "url": "https://flash.jin10.com/detail/20260401004225097800",
          "source": "金十数据",
          "ranks": [
            4
          ],
          "is_new": false,
          "appearance_count": 1,
          "time_info": "00时50分"
        },
        {
          "title": "巴菲特：押注苹果赚了1000亿但卖早了，目前美股不便宜、不抄底，预警银行体系脆弱迹象",
          "url": "https://wallstreetcn.com/articles/3768902",
          "source": "华尔街见闻",
          "ranks": [
            8,
            5,
            4,
            3,
            2
          ],
          "is_new": false,
          "appearance_count": 13,
          "time_info": "[06时23分 ~ 22时24分]"
        },
        {
          "title": "美股收盘：美伊均释放冲突缓和言论 道指飙升逾1100点 纳指涨3.8%",
          "url": "https://www.cls.cn/detail/2331315",
          "source": "财联社热门",
          "ranks": [
            13,
            4,
            2
          ],
          "is_new": false,
          "appearance_count": 6,
          "time_info": "[06时23分 ~ 14时20分]"
        },
        {
          "title": "鲍威尔表态提振美债反弹，但美股高开低走，半导体指数跌超4%，美元五连涨",
          "url": "https://wallstreetcn.com/articles/3768684",
          "source": "华尔街见闻",
          "ranks": [
            5,
            6
          ],
          "is_new": false,
          "appearance_count": 9,
          "time_info": "[00时50分 ~ 06时23分]"
        },
        {
          "title": "美股黄金全线大涨！伊朗总统称伊方愿在诉求满足前提下结束战争",
          "url": "https://www.cls.cn/detail/2331277",
          "source": "财联社热门",
          "ranks": [
            13,
            11,
            6,
            5,
            3
          ],
          "is_new": false,
          "appearance_count": 6,
          "time_info": "[05时27分 ~ 12时38分]"
        },
        {
          "title": "市场押注冲突缓和 美股三大期指齐涨近1% | 今夜看点",
          "url": "https://www.cls.cn/detail/2330950",
          "source": "财联社热门",
          "ranks": [
            11,
            9,
            8
          ],
          "is_new": false,
          "appearance_count": 12,
          "time_info": "[00时50分 ~ 09时17分]"
        },
        {
          "title": "巴菲特：在苹果上赚了1000亿，但卖早了；目前美股不便宜，不抄底",
          "url": "https://wallstreetcn.com/articles/3768902",
          "source": "华尔街见闻",
          "ranks": [
            9,
            8
          ],
          "is_new": false,
          "appearance_count": 8,
          "time_info": "[00时50分 ~ 05时27分]"
        },
        {
          "title": "美股后续会怎么走",
          "url": "https://search.bilibili.com/all?keyword=%E7%BE%8E%E8%82%A1%E5%90%8E%E7%BB%AD%E4%BC%9A%E6%80%8E%E4%B9%88%E8%B5%B0",
          "source": "bilibili 热搜",
          "ranks": [
            30,
            29
          ],
          "is_new": false,
          "appearance_count": 4,
          "time_info": "[00时50分 ~ 03时46分]"
        },
        {
          "title": "美股暴涨 三大股指悉数收高",
          "url": "https://www.baidu.com/s?wd=%E7%BE%8E%E8%82%A1%E6%9A%B4%E6%B6%A8+%E4%B8%89%E5%A4%A7%E8%82%A1%E6%8C%87%E6%82%89%E6%95%B0%E6%94%B6%E9%AB%98",
          "source": "百度热搜",
          "ranks": [
            7
          ],
          "is_new": false,
          "appearance_count": 2,
          "time_info": "[09时16分 ~ 09时17分]"
        },
        {
          "title": "半导体ETF收涨超5.7%，在3月份收官日领跑美股行业ETF，一季度能源业ETF涨37.9%",
          "url": "https://wallstreetcn.com/livenews/3080358",
          "source": "华尔街见闻-快讯",
          "ranks": [
            6,
            29
          ],
          "is_new": false,
          "appearance_count": 2,
          "time_info": "[04时31分 ~ 05时27分]"
        },
        {
          "title": "黄金ETF收跌将近3.8%，领跌美股大类资产类ETF，一季度布油基金涨超83%",
          "url": "https://wallstreetcn.com/livenews/3080383",
          "source": "华尔街见闻-快讯",
          "ranks": [
            6,
            19
          ],
          "is_new": false,
          "appearance_count": 2,
          "time_info": "[05时27分 ~ 06时23分]"
        },
        {
          "title": "美股创下去年5月以来的最大单日涨幅 月线仍跌约5%",
          "url": "https://flash.jin10.com/detail/20260401040945485800",
          "source": "金十数据",
          "ranks": [
            8,
            26
          ],
          "is_new": false,
          "appearance_count": 2,
          "time_info": "[04时31分 ~ 05时27分]"
        },
        {
          "title": "美元指数短线小幅走低，现报99.51。美股期货短线小幅走低，纳斯达克100指数期货涨幅收窄至0.9%。美国10年期国债收益率短线拉升，现报4.292%。现货黄金短线拉升约7美元，现报4743.31美元/盎司。",
          "url": "https://wallstreetcn.com/livenews/3080918",
          "source": "华尔街见闻-快讯",
          "ranks": [
            6
          ],
          "is_new": false,
          "appearance_count": 1,
          "time_info": "20时48分"
        },
        {
          "title": "美股三大指数高开 耐克跌超12%",
          "url": "https://www.baidu.com/s?wd=%E7%BE%8E%E8%82%A1%E4%B8%89%E5%A4%A7%E6%8C%87%E6%95%B0%E9%AB%98%E5%BC%80+%E8%80%90%E5%85%8B%E8%B7%8C%E8%B6%8512%25",
          "source": "百度热搜",
          "ranks": [
            9
          ],
          "is_new": true,
          "appearance_count": 1,
          "time_info": "22时24分"
        },
        {
          "title": "金十图示：2026年03月31日（周二）美股热门股票行情一览（美股收盘）",
          "url": "https://flash.jin10.com/detail/20260401040550571800",
          "source": "金十数据",
          "ranks": [
            10
          ],
          "is_new": false,
          "appearance_count": 1,
          "time_info": "04时31分"
        },
        {
          "title": "金十图示：2026年03月31日（周二）美股热门股票行情一览（美股盘中）",
          "url": "https://flash.jin10.com/detail/20260401003322867800",
          "source": "金十数据",
          "ranks": [
            12
          ],
          "is_new": false,
          "appearance_count": 1,
          "time_info": "00时50分"
        },
        {
          "title": "金十图示：2026年03月31日（周二）热门中概股行情一览（美股收盘）",
          "url": "https://flash.jin10.com/detail/20260401040516716800",
          "source": "金十数据",
          "ranks": [
            12
          ],
          "is_new": false,
          "appearance_count": 1,
          "time_info": "04时31分"
        },
        {
          "title": "金十图示：2026年03月31日（周二）热门中概股行情一览（美股盘中）",
          "url": "https://flash.jin10.com/detail/20260401003320625800",
          "source": "金十数据",
          "ranks": [
            13
          ],
          "is_new": false,
          "appearance_count": 1,
          "time_info": "00时50分"
        },
        {
          "title": "美股收盘：三大股指大涨 纳指涨3.8%",
          "url": "https://flash.jin10.com/detail/20260401040119992800",
          "source": "金十数据",
          "ranks": [
            13
          ],
          "is_new": false,
          "appearance_count": 1,
          "time_info": "04时31分"
        },
        {
          "title": "纽约银日内涨幅达7.0%，报75.52美元/盎司。 临近美股收盘，纳斯达克100指数涨幅扩大至3.5%，标普500指数涨3%，道指涨1152点、涨幅2.55%，纳指涨超3.9%，生物科技指数涨4.65%，半导体指数涨6.1%，银行指数涨3.6%，罗素2000指数涨3.3%。",
          "url": "https://wallstreetcn.com/livenews/3080348",
          "source": "华尔街见闻-快讯",
          "ranks": [
            14
          ],
          "is_new": false,
          "appearance_count": 1,
          "time_info": "04时31分"
        },
        {
          "title": "美股涨幅扩大，纳指涨超1%。",
          "url": "https://wallstreetcn.com/livenews/3080958",
          "source": "华尔街见闻-快讯",
          "ranks": [
            14
          ],
          "is_new": true,
          "appearance_count": 1,
          "time_info": "22时24分"
        },
        {
          "title": "美股盘初，主要行业ETF普涨，全球航空业ETF、半导体ETF涨超2%，全球科技股指数ETF涨1.6%。",
          "url": "https://wallstreetcn.com/livenews/3080956",
          "source": "华尔街见闻-快讯",
          "ranks": [
            15
          ],
          "is_new": true,
          "appearance_count": 1,
          "time_info": "22时24分"
        },
        {
          "title": "美国3月ADP就业数据公布后，美元指数、美股期货短线波动不大",
          "url": "https://wallstreetcn.com/livenews/3080904",
          "source": "华尔街见闻-快讯",
          "ranks": [
            18
          ],
          "is_new": false,
          "appearance_count": 1,
          "time_info": "20时48分"
        },
        {
          "title": "美股盘初：纳指涨0.7%，大型科技股普涨",
          "url": "https://wallstreetcn.com/livenews/3080946",
          "source": "华尔街见闻-快讯",
          "ranks": [
            22
          ],
          "is_new": true,
          "appearance_count": 1,
          "time_info": "22时24分"
        },
        {
          "title": "交易员称美股本轮劲扬主要由空头回补所致 并非伊朗和平前景",
          "url": "https://wallstreetcn.com/livenews/3080893",
          "source": "华尔街见闻-快讯",
          "ranks": [
            27
          ],
          "is_new": false,
          "appearance_count": 1,
          "time_info": "20时48分"
        }
      ]
    },
    {
      "keyword_group": "白银",
      "match_count": 5,
      "titles": [
        {
          "title": "上海黄金交易所黄金T+D 4月1日（周三）早盘盘初上涨2.89%报1047.88元/克；<br/>上海黄金交易所白银T+D 4月1日（周三）早盘盘初上涨4.88%报18998.0元/千克。",
          "url": "https://flash.jin10.com/detail/20260401090121836800",
          "source": "金十数据",
          "ranks": [
            3
          ],
          "is_new": false,
          "appearance_count": 1,
          "time_info": "09时17分"
        },
        {
          "title": "“快钱已出局”！白银3月暴跌20%后，华尔街再次喊出100美元目标",
          "url": "https://flash.jin10.com/detail/20260401083647607800",
          "source": "金十数据",
          "ranks": [
            17
          ],
          "is_new": false,
          "appearance_count": 1,
          "time_info": "09时17分"
        },
        {
          "title": "金十图示：2026年04月01日（周三）白银ETF持仓报告",
          "url": "https://flash.jin10.com/detail/20260401120111622800",
          "source": "金十数据",
          "ranks": [
            19
          ],
          "is_new": false,
          "appearance_count": 1,
          "time_info": "12时38分"
        },
        {
          "title": "上海黄金交易所黄金T+D 3月31日（周二）晚盘收盘上涨1.67%报1035.5元/克；<br/>上海黄金交易所白银T+D 3月31日（周二）晚盘收盘上涨3.93%报18825.0元/千克。",
          "url": "https://flash.jin10.com/detail/20260401023033444800",
          "source": "金十数据",
          "ranks": [
            20
          ],
          "is_new": false,
          "appearance_count": 1,
          "time_info": "03时46分"
        },
        {
          "title": "全球最大白银ETF--iShares Silver Trust持仓较上日减少14.08吨，当前持仓量为15274.28吨。欢迎点击查看数据中心...",
          "url": "https://flash.jin10.com/detail/20260401060953827800",
          "source": "金十数据",
          "ranks": [
            27
          ],
          "is_new": false,
          "appearance_count": 1,
          "time_info": "07时23分"
        }
      ]
    }
  ],
  "report_image_url": "https://github.com/siebenwan-oss/TrendRadar.git/img/news.jpg"
}