{
  "generated_at": "2026-05-18T14:05:00.951861+08:00",
  "total_titles_processed": 921,
  "failed_sources": [],
  "trends": [
    {
      "keyword_group": "白银",
      "match_count": 6,
      "titles": [
        {
          "title": "白银价格“过山车”：强势七连涨后大跳水，何时重回巅峰？",
          "url": "https://m.thepaper.cn/newsDetail_forward_33186880",
          "source": "澎湃新闻",
          "ranks": [
            5,
            6
          ],
          "is_new": false,
          "appearance_count": 11,
          "time_info": "[00时42分 ~ 09时57分]"
        },
        {
          "title": "现货黄金开跌0.2%，现货白银开盘快速跌1%。",
          "url": "https://flash.jin10.com/detail/20260518060131657800",
          "source": "金十数据",
          "ranks": [
            4,
            22
          ],
          "is_new": false,
          "appearance_count": 2,
          "time_info": "[06时41分 ~ 07时45分]"
        },
        {
          "title": "白银价格“过山车” 何时重回巅峰",
          "url": "https://www.toutiao.com/trending/7640785693907619371/",
          "source": "今日头条",
          "ranks": [
            27,
            28
          ],
          "is_new": false,
          "appearance_count": 3,
          "time_info": "[00时42分 ~ 02时49分]"
        },
        {
          "title": "金十图示：2026年05月18日（周一）白银ETF持仓报告",
          "url": "https://flash.jin10.com/detail/20260518064413806800",
          "source": "金十数据",
          "ranks": [
            8
          ],
          "is_new": false,
          "appearance_count": 1,
          "time_info": "07时45分"
        },
        {
          "title": "现货白银日内涨幅达1.00%，现报76.67美元/盎司。",
          "url": "https://flash.jin10.com/detail/20260518063201642800",
          "source": "金十数据",
          "ranks": [
            15
          ],
          "is_new": false,
          "appearance_count": 1,
          "time_info": "07时45分"
        },
        {
          "title": "A股贵金属板块多股低开，白银有色跌超4%，湖南白银跌超3%，招金黄金、中金黄金等跟跌。",
          "url": "https://flash.jin10.com/detail/20260518092822970800",
          "source": "金十数据",
          "ranks": [
            29
          ],
          "is_new": false,
          "appearance_count": 1,
          "time_info": "09时57分"
        }
      ]
    },
    {
      "keyword_group": "美股",
      "match_count": 5,
      "titles": [
        {
          "title": "环球下周看点：英伟达财报与美联储会议纪要来袭 美股行情迎关键考验",
          "url": "https://www.cls.cn/detail/2373249",
          "source": "财联社热门",
          "ranks": [
            8,
            9,
            10
          ],
          "is_new": false,
          "appearance_count": 11,
          "time_info": "[00时42分 ~ 09时57分]"
        },
        {
          "title": "美股和金银开盘大跌，但美国 4 月工业数据超预期，纽约联储制造业指数创近 4 年新高，对此你怎么看？",
          "url": "https://www.zhihu.com/question/2038737314017432936",
          "source": "知乎",
          "ranks": [
            14,
            13,
            12
          ],
          "is_new": false,
          "appearance_count": 4,
          "time_info": "[06时41分 ~ 09时57分]"
        },
        {
          "title": "美股股指期货周一小幅低开，其中道指期货跌0.3%。",
          "url": "https://flash.jin10.com/detail/20260518060027813800",
          "source": "金十数据",
          "ranks": [
            6,
            24
          ],
          "is_new": false,
          "appearance_count": 2,
          "time_info": "[06时41分 ~ 07时45分]"
        },
        {
          "title": "美股不祥信号浮现？美债收益率狂飙 一文解析背后三大推手",
          "url": "https://www.cls.cn/detail/2373864",
          "source": "财联社热门",
          "ranks": [
            10
          ],
          "is_new": false,
          "appearance_count": 2,
          "time_info": "[14时04分 ~ 14时05分]"
        },
        {
          "title": "史上最大IPO来袭！SpaceX据传最早6月12日登陆美股 目标估值高达1.75万亿美元",
          "url": "https://www.cls.cn/detail/2373172",
          "source": "财联社热门",
          "ranks": [
            13
          ],
          "is_new": false,
          "appearance_count": 2,
          "time_info": "[07时44分 ~ 07时45分]"
        }
      ]
    }
  ],
  "report_image_url": "https://github.com/siebenwan-oss/TrendRadar.git/img/news.jpg"
}